build/lib/pythonrunner/__init__.py
build/lib/pythonrunner/__main__.py
build/lib/pythonrunner/pythonrunner.py
build/lib/pythonrunner/worker.py
pyrunx-0.1.18.dist-info/licenses/LICENSE
pythonrunner/__init__.py
pythonrunner/__main__.py
pythonrunner/pythonrunner.py
pythonrunner/worker.py
pyrunx-0.1.18.dist-info/METADATA
pyrunx-0.1.18.dist-info/WHEEL
pyrunx-0.1.18.dist-info/entry_points.txt
pyrunx-0.1.18.dist-info/top_level.txt
pyrunx-0.1.18.dist-info/RECORD
