Metadata-Version: 2.4
Name: pyrunx
Version: 0.1.18
Summary: Simple project that allows you to run python scripts 
Author: 6C656C65
License-Expression: MIT
Project-URL: Documentation, https://github.com/6C656C65/pythonrunner/wiki
Project-URL: Issue tracker, https://github.com/6C656C65/pythonrunner/issues
Classifier: Development Status :: 5 - Production/Stable
Classifier: Intended Audience :: Developers
Classifier: Natural Language :: English
Classifier: Operating System :: OS Independent
Classifier: Programming Language :: Python :: 3.8
Classifier: Programming Language :: Python :: 3.9
Classifier: Programming Language :: Python :: 3.10
Classifier: Programming Language :: Python :: 3.11
Classifier: Programming Language :: Python :: 3.12
Classifier: Topic :: Internet
Classifier: Topic :: Software Development :: Libraries
Classifier: Topic :: Software Development :: Libraries :: Python Modules
Classifier: Topic :: Utilities
Classifier: Typing :: Typed
License-File: LICENSE
Requires-Dist: rich-argparse>=1.7.0
Requires-Dist: colorlog>=6.9.0
Requires-Dist: discord.py>=2.5.2
Requires-Dist: requests>=2.31.0
Requires-Dist: pyyaml>=6.0.2
Dynamic: license-file
